google/events/cloud/alloydb/__init__.py
google/events/cloud/alloydb/gapic_version.py
google/events/cloud/alloydb/py.typed
google/events/cloud/alloydb_v1/__init__.py
google/events/cloud/alloydb_v1/gapic_version.py
google/events/cloud/alloydb_v1/py.typed
google/events/cloud/alloydb_v1/services/__init__.py
google/events/cloud/alloydb_v1/types/__init__.py
google/events/cloud/alloydb_v1/types/data.py
google/events/cloud/apigateway/__init__.py
google/events/cloud/apigateway/gapic_version.py
google/events/cloud/apigateway/py.typed
google/events/cloud/apigateway_v1/__init__.py
google/events/cloud/apigateway_v1/gapic_version.py
google/events/cloud/apigateway_v1/py.typed
google/events/cloud/apigateway_v1/services/__init__.py
google/events/cloud/apigateway_v1/types/__init__.py
google/events/cloud/apigateway_v1/types/data.py
google/events/cloud/apigeeregistry/__init__.py
google/events/cloud/apigeeregistry/gapic_version.py
google/events/cloud/apigeeregistry/py.typed
google/events/cloud/apigeeregistry_v1/__init__.py
google/events/cloud/apigeeregistry_v1/gapic_version.py
google/events/cloud/apigeeregistry_v1/py.typed
google/events/cloud/apigeeregistry_v1/services/__init__.py
google/events/cloud/apigeeregistry_v1/types/__init__.py
google/events/cloud/apigeeregistry_v1/types/data.py
google/events/cloud/audit/__init__.py
google/events/cloud/audit/gapic_version.py
google/events/cloud/audit/py.typed
google/events/cloud/audit_v1/__init__.py
google/events/cloud/audit_v1/gapic_version.py
google/events/cloud/audit_v1/py.typed
google/events/cloud/audit_v1/services/__init__.py
google/events/cloud/audit_v1/types/__init__.py
google/events/cloud/audit_v1/types/data.py
google/events/cloud/batch/__init__.py
google/events/cloud/batch/gapic_version.py
google/events/cloud/batch/py.typed
google/events/cloud/batch_v1/__init__.py
google/events/cloud/batch_v1/gapic_version.py
google/events/cloud/batch_v1/py.typed
google/events/cloud/batch_v1/services/__init__.py
google_events-0.13.0.dist-info/LICENSE
google_events-0.13.0.dist-info/METADATA
google_events-0.13.0.dist-info/WHEEL
google_events-0.13.0.dist-info/top_level.txt
google_events-0.13.0.dist-info/RECORD
