Metadata-Version: 2.1
Name: google-events
Version: 0.13.0
Summary: Google Cloudevents library
Home-page: https://github.com/googleapis/google-cloudevents-python/
Author: Google LLC
Author-email: googleapis-packages@google.com
License: Apache License 2.0
Platform: Posix
Platform: MacOS X
Platform: Windows
Classifier: Intended Audience :: Developers
Classifier: License :: OSI Approved :: Apache Software License
Classifier: Programming Language :: Python
Classifier: Programming Language :: Python :: 3
Classifier: Programming Language :: Python :: 3.7
Classifier: Programming Language :: Python :: 3.8
Classifier: Programming Language :: Python :: 3.9
Classifier: Programming Language :: Python :: 3.10
Classifier: Programming Language :: Python :: 3.11
Classifier: Operating System :: OS Independent
Classifier: Topic :: Internet
Requires-Python: >=3.7
License-File: LICENSE
Requires-Dist: proto-plus>=1.22.0
Requires-Dist: protobuf>=4.21.5
